pywd
