Metadata-Version: 1.1
Name: pywd
Version: 0.0.3
Summary: Command-line Python password generator
Home-page: http://www.github.com/zafia/pywd
Author: Safia Abdalla
Author-email: seabdalla@gmail.com
License: MIT License
Platform: UNKNOWN
Classifier: Development Status :: 4 - Beta
Classifier: Environment :: Web Environment
Classifier: Intended Audience :: Developers
Classifier: Intended Audience :: End Users/Desktop
Classifier: License :: OSI Approved :: MIT License
Classifier: Natural Language :: English
Classifier: Programming Language :: Python :: 3.4
